<?xml version="1.0" encoding="UTF-8"?><record_update sys_domain="global" table="sysevent_email_action">
    <sysevent_email_action action="INSERT_OR_UPDATE">
        <action_insert>false</action_insert>
        <action_update>false</action_update>
        <active>true</active>
        <advanced_condition/>
        <affected_field_on_event/>
        <category display_value="Uncategorized" name="Uncategorized">c97d83137f4432005f58108c3ffa917a</category>
        <collection>x_cama2_survey_dis_survey_distribution</collection>
        <condition/>
        <content_type>text/html</content_type>
        <default_interval/>
        <description/>
        <digest_from/>
        <digest_html/>
        <digest_reply_to/>
        <digest_separator_html><![CDATA[<p>&nbsp;</p>
<hr />
<p>&nbsp;</p>]]></digest_separator_html>
        <digest_separator_text><![CDATA[\n--------------------------------------------------------------------------------\n]]></digest_separator_text>
        <digest_subject/>
        <digest_template/>
        <digest_text/>
        <digestable>false</digestable>
        <enable_dynamic_translation>false</enable_dynamic_translation>
        <event_name>survey.distro.reminder</event_name>
        <event_parm_1>false</event_parm_1>
        <event_parm_2>false</event_parm_2>
        <exclude_delegates>false</exclude_delegates>
        <force_delivery>false</force_delivery>
        <from/>
        <generation_type>event</generation_type>
        <importance/>
        <include_attachments>false</include_attachments>
        <item>event.parm1</item>
        <item_table/>
        <mandatory>false</mandatory>
        <message/>
        <message_html><![CDATA[<p><span style="font-size: 12pt;">A MAF for ${current.product} |&nbsp; ${URI_REF} is still currently awaiting review.</span></p>
<p><span style="font-size: 12pt;">${current.product_owner}, please review the survey. When complete please select the '<strong>Completed/Rejection</strong>' options. If completed, the survey will be listed as complete on the dashboard, if there is a reason not to approve the survey and rejection is selected, a notification to the ${current.assigned_to} will be sent and adjustments can be made to the existing survey.</span></p>
<p>&nbsp;</p>
<p><span style="font-size: 12pt;">A link to the survey is also on your MAF Dashboard located within the Service Portal.</span></p>
<p><span style="font-size: 12pt;">Thank you!</span></p>]]></message_html>
        <message_list/>
        <message_text/>
        <name>Survey Distro - Reminder</name>
        <omit_watermark>false</omit_watermark>
        <order>100</order>
        <push_message_only>false</push_message_only>
        <recipient_fields/>
        <recipient_groups/>
        <recipient_users/>
        <reply_to/>
        <send_self>true</send_self>
        <sms_alternate/>
        <style/>
        <subject>Reminder MAF Survey Notification - ${current.product} is currently awaiting review</subject>
        <subscribable>false</subscribable>
        <sys_class_name>sysevent_email_action</sys_class_name>
        <sys_created_by>vahojehbrooks@gmail.com</sys_created_by>
        <sys_created_on>2024-06-28 16:33:06</sys_created_on>
        <sys_domain>global</sys_domain>
        <sys_domain_path>/</sys_domain_path>
        <sys_id>7a24f44ec3030210e961bdbc050131e3</sys_id>
        <sys_mod_count>0</sys_mod_count>
        <sys_name>Survey Distro - Reminder</sys_name>
        <sys_overrides/>
        <sys_package display_value="Survey Distribution" source="x_cama2_survey_dis">c5c93bf01bedbd50f9c8ebd22a4bcb95</sys_package>
        <sys_policy/>
        <sys_scope display_value="Survey Distribution">c5c93bf01bedbd50f9c8ebd22a4bcb95</sys_scope>
        <sys_update_name>sysevent_email_action_7a24f44ec3030210e961bdbc050131e3</sys_update_name>
        <sys_updated_by>vahojehbrooks@gmail.com</sys_updated_by>
        <sys_updated_on>2024-06-28 16:33:06</sys_updated_on>
        <sys_version>2</sys_version>
        <template display_value="Unsubscribe and Preferences">7ed0481f3b0b2200c869c2c703efc487</template>
        <type>email</type>
        <weight>0</weight>
    </sysevent_email_action>
</record_update>
